[{"CaptionString": {"key": "53EE42EF4EBDE7E414D11EAE5027E6E1", "namespace": "", "string": "$USER_NAME_OR_ID has pulled off $TARGET_VALUE shotgun sliding kills."}, "CondensedCaptionString": {"key": "6B399CA748D15E943A0780BC2B52DB4B", "namespace": "", "string": "$USER_NAME_OR_ID is one badass Vault Hunter!"}, "LargeImageUrl": "activity_feed_shotgun2_large.png", "SmallImageUrl": "activity_feed_shotgun2_small.png", "URLBrowserActionData": ["OakAction_OpenURL", "/Game/GameData/Social/ActivityFeeds/OakAction_OpenURL"], "_apoc_data_ver": 17, "_jwp_export_idx": 1, "_jwp_is_asset": true, "_jwp_object_name": "ShotgunSlidingKills_ActivityFeed", "export_type": "ActivityFeedReward"}]