[{"AnimationList": [{"_jwp_arr_idx": 0, "key": "Combat/AS_Dodge_Grenade_Idle_L", "value": ["AS_Dodge_Grenade_Idle_L", "/Game/Enemies/Nog/_Shared/Animation/Combat/AS_Dodge_Grenade_Idle_L"]}, {"_jwp_arr_idx": 1, "key": "Combat/AS_Dodge_Grenade_Idle_R", "value": ["AS_Dodge_Grenade_Idle_R", "/Game/Enemies/Nog/_Shared/Animation/Combat/AS_Dodge_Grenade_Idle_R"]}], "_apoc_data_ver": 17, "_jwp_export_idx": 1, "_jwp_is_asset": true, "_jwp_object_name": "ASet_Nog_Vehicle_Dodge", "export_type": "GbxAnimSet"}]