[{"DefaultInstance": {"CollisionProfileName": "BlockAll", "CollisionResponses": {"ResponseArray": [{"Channel": "UseTrace", "Response": "ECR_Block", "_jwp_arr_idx": 0}]}, "ObjectType": "ECC_WorldStatic"}, "_apoc_data_ver": 17, "_jwp_export_idx": 1, "_jwp_is_asset": false, "_jwp_object_name": "BodySetup_0", "export_type": "BodySetup"}, {"_jwp_export_idx": 2, "_jwp_is_asset": false, "_jwp_object_name": "NavCollision_8", "export_type": "NavCollision"}, {"ExtendedBounds": {"BoxExtent": {"x": 3309.1577, "y": 3184.5635, "z": 1552.535}, "Origin": {"x": -599.7964, "y": -3182.4326, "z": 849.77045}, "SphereRadius": 3982.736}, "LODGroup": "Medium", "LightMapCoordinateIndex": 1, "LightMapResolution": 64, "LightmapUVDensity": 9053.513, "MinResolutionForPrePaddedLightmapUV": 64, "StaticMaterials": [{"ImportedMaterialSlotName": "03 - Default", "MaterialInterface": ["MI_Eden6_LeavesLarge_01", "/Game/LevelArt/Environments/Eden6/Landscape/Vegetation/Trees/Canopies/Model/Materials/MI_Eden6_LeavesLarge_01"], "MaterialSlotName": "bark", "UVChannelData": {"LocalUVDensities": 0.0, "bInitialized": true, "bOverrideDensities": false}, "_jwp_arr_idx": 0}], "_jwp_export_idx": 3, "_jwp_is_asset": true, "_jwp_object_name": "SM_Eden6_TreeBranch_Canopy_V4b", "export_type": "StaticMesh"}]