[{"BoneModStates": [{"Blend": {"BlendOption": "EAlphaBlendOption::Linear", "BlendTime": 0.2, "CustomCurve": {"export": 0}}, "Bones": [{"BoneName": "Hips", "Rotation": {"pitch": 0.0, "roll": 0.0, "yaw": 0.0}, "Scale": {"x": 0.983, "y": 0.983, "z": 0.983}, "Translation": {"x": 0.0, "y": 0.0, "z": 0.0}, "_jwp_arr_idx": 0}, {"BoneName": "Spine1", "Rotation": {"pitch": 0.0, "roll": 0.0, "yaw": 0.0}, "Scale": {"x": 1.0, "y": 1.0, "z": 1.0}, "Translation": {"x": 0.18608761, "y": -0.015057743, "z": 0.0}, "_jwp_arr_idx": 1}, {"BoneName": "Spine2", "Rotation": {"pitch": 0.0, "roll": 0.0, "yaw": 0.0}, "Scale": {"x": 1.0742625, "y": 1.0742625, "z": 1.0742625}, "Translation": {"x": -0.68979836, "y": 0.0007910831, "z": 0.0}, "_jwp_arr_idx": 2}, {"BoneName": "Spine3", "Rotation": {"pitch": 0.0, "roll": 0.0, "yaw": 0.0}, "Scale": {"x": 1.1439394, "y": 1.1439394, "z": 1.1439394}, "Translation": {"x": -1.0, "y": 0.0, "z": 0.0}, "_jwp_arr_idx": 3}, {"BoneName": "Spine4", "Rotation": {"pitch": 0.0, "roll": 0.0, "yaw": 0.0}, "Scale": {"x": 1.2971854, "y": 1.2971854, "z": 1.2971854}, "Translation": {"x": -1.2667952, "y": -0.002481748, "z": 0.0}, "_jwp_arr_idx": 4}, {"BoneName": "SpineEnd", "Rotation": {"pitch": 0.0, "roll": 0.0, "yaw": 0.0}, "Scale": {"x": 0.6949585, "y": 0.6949585, "z": 0.6949585}, "Translation": {"x": 1.2541132, "y": 0.0012642113, "z": 0.0}, "_jwp_arr_idx": 5}, {"BoneName": "Spine_End_Offset", "Rotation": {"pitch": 0.0, "roll": 0.0, "yaw": 0.0}, "Scale": {"x": 0.9182737, "y": 0.9182737, "z": 0.9182737}, "Translation": {"x": 0.0, "y": 0.0, "z": 0.0}, "_jwp_arr_idx": 6}, {"BoneName": "Neck1", "Rotation": {"pitch": 0.0, "roll": 0.0, "yaw": 0.0}, "Scale": {"x": 1.3, "y": 1.3, "z": 1.3}, "Translation": {"x": 0.0, "y": 0.0, "z": 0.0}, "_jwp_arr_idx": 7}, {"BoneName": "Neck2", "Rotation": {"pitch": 0.0, "roll": 0.0, "yaw": 0.0}, "Scale": {"x": 0.84615386, "y": 0.84615386, "z": 0.84615386}, "Translation": {"x": 0.0, "y": 0.0, "z": 0.0}, "_jwp_arr_idx": 8}, {"BoneName": "Head", "Rotation": {"pitch": 0.0, "roll": 0.0, "yaw": 0.0}, "Scale": {"x": 0.9090909, "y": 0.9090909, "z": 0.9090909}, "Translation": {"x": -1.9040847, "y": 0.6302111, "z": 0.0}, "_jwp_arr_idx": 9}, {"BoneName": "FaceRoot", "Rotation": {"pitch": 0.0, "roll": 0.0, "yaw": 0.0}, "Scale": {"x": 1.0, "y": 1.0, "z": 1.0}, "Translation": {"x": 0.0, "y": 0.0, "z": 0.0}, "_jwp_arr_idx": 10}, {"BoneName": "Upperlip", "Rotation": {"pitch": 0.0, "roll": 0.0, "yaw": 0.0}, "Scale": {"x": 1.0, "y": 1.0, "z": 1.0}, "Translation": {"x": 0.0, "y": 0.0, "z": 0.0}, "_jwp_arr_idx": 11}, {"BoneName": "L_UpperLip", "Rotation": {"pitch": 0.0, "roll": 0.0, "yaw": 0.0}, "Scale": {"x": 1.0, "y": 1.0, "z": 1.0}, "Translation": {"x": 0.0, "y": 0.0, "z": 0.0}, "_jwp_arr_idx": 12}, {"BoneName": "L_UpperLipCorner", "Rotation": {"pitch": 0.0, "roll": 0.0, "yaw": 0.0}, "Scale": {"x": 1.0, "y": 1.0, "z": 1.0}, "Translation": {"x": 0.0, "y": 0.0, "z": 0.0}, "_jwp_arr_idx": 13}, {"BoneName": "L_MouthCorner", "Rotation": {"pitch": 0.0, "roll": 0.0, "yaw": 0.0}, "Scale": {"x": 1.0, "y": 1.0, "z": 1.0}, "Translation": {"x": 0.0, "y": 0.0, "z": 0.0}, "_jwp_arr_idx": 14}, {"BoneName": "UpperLipFold", "Rotation": {"pitch": 0.0, "roll": 0.0, "yaw": 0.0}, "Scale": {"x": 1.0, "y": 1.0, "z": 1.0}, "Translation": {"x": 0.0, "y": 0.0, "z": 0.0}, "_jwp_arr_idx": 15}, {"BoneName": "L_Sneer", "Rotation": {"pitch": 0.0, "roll": 0.0, "yaw": 0.0}, "Scale": {"x": 1.0, "y": 1.0, "z": 1.0}, "Translation": {"x": 0.0, "y": 0.0, "z": 0.0}, "_jwp_arr_idx": 16}, {"BoneName": "L_NasalLabiaFold", "Rotation": {"pitch": 0.0, "roll": 0.0, "yaw": 0.0}, "Scale": {"x": 1.0, "y": 1.0, "z": 1.0}, "Translation": {"x": 0.0, "y": 0.0, "z": 0.0}, "_jwp_arr_idx": 17}, {"BoneName": "L_Cheek", "Rotation": {"pitch": 0.0, "roll": 0.0, "yaw": 0.0}, "Scale": {"x": 1.0, "y": 1.0, "z": 1.0}, "Translation": {"x": 0.0, "y": 0.0, "z": 0.0}, "_jwp_arr_idx": 18}, {"BoneName": "Nose_End", "Rotation": {"pitch": 0.0, "roll": 0.0, "yaw": 0.0}, "Scale": {"x": 1.0, "y": 1.0, "z": 1.0}, "Translation": {"x": 0.0, "y": 0.0, "z": 0.0}, "_jwp_arr_idx": 19}, {"BoneName": "L_NasalCorner", "Rotation": {"pitch": 0.0, "roll": 0.0, "yaw": 0.0}, "Scale": {"x": 1.0, "y": 1.0, "z": 1.0}, "Translation": {"x": 0.0, "y": 0.0, "z": 0.0}, "_jwp_arr_idx": 20}, {"BoneName": "L_CheekBone", "Rotation": {"pitch": 0.0, "roll": 0.0, "yaw": 0.0}, "Scale": {"x": 1.0, "y": 1.0, "z": 1.0}, "Translation": {"x": 0.0, "y": 0.0, "z": 0.0}, "_jwp_arr_idx": 21}, {"BoneName": "L_Eye", "Rotation": {"pitch": 0.0, "roll": 0.0, "yaw": 0.0}, "Scale": {"x": 1.0, "y": 1.0, "z": 1.0}, "Translation": {"x": 0.0, "y": 0.0, "z": 0.0}, "_jwp_arr_idx": 22}, {"BoneName": "L_LowerInsideEyelid", "Rotation": {"pitch": 0.0, "roll": 0.0, "yaw": 0.0}, "Scale": {"x": 1.0, "y": 1.0, "z": 1.0}, "Translation": {"x": 0.0, "y": 0.0, "z": 0.0}, "_jwp_arr_idx": 23}, {"BoneName": "L_LowerMiddleEyelid", "Rotation": {"pitch": 0.0, "roll": 0.0, "yaw": 0.0}, "Scale": {"x": 1.0, "y": 1.0, "z": 1.0}, "Translation": {"x": 0.0, "y": 0.0, "z": 0.0}, "_jwp_arr_idx": 24}, {"BoneName": "L_LowerOutsideEyelid", "Rotation": {"pitch": 0.0, "roll": 0.0, "yaw": 0.0}, "Scale": {"x": 1.0, "y": 1.0, "z": 1.0}, "Translation": {"x": 0.0, "y": 0.0, "z": 0.0}, "_jwp_arr_idx": 25}, {"BoneName": "L_UpperInsideEyelid", "Rotation": {"pitch": 0.0, "roll": 0.0, "yaw": 0.0}, "Scale": {"x": 1.0, "y": 1.0, "z": 1.0}, "Translation": {"x": 0.0, "y": 0.0, "z": 0.0}, "_jwp_arr_idx": 26}, {"BoneName": "L_UpperMiddleEyelid", "Rotation": {"pitch": 0.0, "roll": 0.0, "yaw": 0.0}, "Scale": {"x": 1.0, "y": 1.0, "z": 1.0}, "Translation": {"x": 0.0, "y": 0.0, "z": 0.0}, "_jwp_arr_idx": 27}, {"BoneName": "L_UpperOutsideEyelid", "Rotation": {"pitch": 0.0, "roll": 0.0, "yaw": 0.0}, "Scale": {"x": 1.0, "y": 1.0, "z": 1.0}, "Translation": {"x": 0.0, "y": 0.0, "z": 0.0}, "_jwp_arr_idx": 28}, {"BoneName": "M_Brow", "Rotation": {"pitch": 0.0, "roll": 0.0, "yaw": 0.0}, "Scale": {"x": 1.0, "y": 1.0, "z": 1.0}, "Translation": {"x": 0.0, "y": 0.0, "z": 0.0}, "_jwp_arr_idx": 29}, {"BoneName": "L_InnerBrow", "Rotation": {"pitch": 0.0, "roll": 0.0, "yaw": 0.0}, "Scale": {"x": 1.0, "y": 1.0, "z": 1.0}, "Translation": {"x": 0.0, "y": 0.0, "z": 0.0}, "_jwp_arr_idx": 30}, {"BoneName": "L_Brow", "Rotation": {"pitch": 0.0, "roll": 0.0, "yaw": 0.0}, "Scale": {"x": 1.0, "y": 1.0, "z": 1.0}, "Translation": {"x": 0.0, "y": 0.0, "z": 0.0}, "_jwp_arr_idx": 31}, {"BoneName": "L_OuterBrow", "Rotation": {"pitch": 0.0, "roll": 0.0, "yaw": 0.0}, "Scale": {"x": 1.0, "y": 1.0, "z": 1.0}, "Translation": {"x": 0.0, "y": 0.0, "z": 0.0}, "_jwp_arr_idx": 32}, {"BoneName": "L_Forehead", "Rotation": {"pitch": 0.0, "roll": 0.0, "yaw": 0.0}, "Scale": {"x": 1.0, "y": 1.0, "z": 1.0}, "Translation": {"x": 0.0, "y": 0.0, "z": 0.0}, "_jwp_arr_idx": 33}, {"BoneName": "L_NasalFlare", "Rotation": {"pitch": 0.0, "roll": 0.0, "yaw": 0.0}, "Scale": {"x": 1.0, "y": 1.0, "z": 1.0}, "Translation": {"x": 0.0, "y": 0.0, "z": 0.0}, "_jwp_arr_idx": 34}, {"BoneName": "Jaw", "Rotation": {"pitch": 0.0, "roll": 0.0, "yaw": 0.0}, "Scale": {"x": 1.0, "y": 1.0, "z": 1.0}, "Translation": {"x": 0.0, "y": 0.0, "z": 0.0}, "_jwp_arr_idx": 35}, {"BoneName": "LowerLip", "Rotation": {"pitch": 0.0, "roll": 0.0, "yaw": 0.0}, "Scale": {"x": 1.0, "y": 1.0, "z": 1.0}, "Translation": {"x": 0.0, "y": 0.0, "z": 0.0}, "_jwp_arr_idx": 36}, {"BoneName": "L_LowerLip", "Rotation": {"pitch": 0.0, "roll": 0.0, "yaw": 0.0}, "Scale": {"x": 1.0, "y": 1.0, "z": 1.0}, "Translation": {"x": 0.0, "y": 0.0, "z": 0.0}, "_jwp_arr_idx": 37}, {"BoneName": "L_LowerLipCorner", "Rotation": {"pitch": 0.0, "roll": 0.0, "yaw": 0.0}, "Scale": {"x": 1.0, "y": 1.0, "z": 1.0}, "Translation": {"x": 0.0, "y": 0.0, "z": 0.0}, "_jwp_arr_idx": 38}, {"BoneName": "LowerLipFold", "Rotation": {"pitch": 0.0, "roll": 0.0, "yaw": 0.0}, "Scale": {"x": 1.0, "y": 1.0, "z": 1.0}, "Translation": {"x": 0.0, "y": 0.0, "z": 0.0}, "_jwp_arr_idx": 39}, {"BoneName": "L_LowerMouthFold", "Rotation": {"pitch": 0.0, "roll": 0.0, "yaw": 0.0}, "Scale": {"x": 1.0, "y": 1.0, "z": 1.0}, "Translation": {"x": 0.0, "y": 0.0, "z": 0.0}, "_jwp_arr_idx": 40}, {"BoneName": "L_LowerLabiaFold", "Rotation": {"pitch": 0.0, "roll": 0.0, "yaw": 0.0}, "Scale": {"x": 1.0, "y": 1.0, "z": 1.0}, "Translation": {"x": 0.0, "y": 0.0, "z": 0.0}, "_jwp_arr_idx": 41}, {"BoneName": "Tongue_01", "Rotation": {"pitch": 0.0, "roll": 0.0, "yaw": 0.0}, "Scale": {"x": 1.0, "y": 1.0, "z": 1.0}, "Translation": {"x": 0.0, "y": 0.0, "z": 0.0}, "_jwp_arr_idx": 42}, {"BoneName": "Tongue_02", "Rotation": {"pitch": 0.0, "roll": 0.0, "yaw": 0.0}, "Scale": {"x": 1.0, "y": 1.0, "z": 1.0}, "Translation": {"x": 0.0, "y": 0.0, "z": 0.0}, "_jwp_arr_idx": 43}, {"BoneName": "Tongue_03", "Rotation": {"pitch": 0.0, "roll": 0.0, "yaw": 0.0}, "Scale": {"x": 1.0, "y": 1.0, "z": 1.0}, "Translation": {"x": 0.0, "y": 0.0, "z": 0.0}, "_jwp_arr_idx": 44}, {"BoneName": "R_LowerLip", "Rotation": {"pitch": 0.0, "roll": 0.0, "yaw": 0.0}, "Scale": {"x": 1.0, "y": 1.0, "z": 1.0}, "Translation": {"x": 0.0, "y": 0.0, "z": 0.0}, "_jwp_arr_idx": 45}, {"BoneName": "R_LowerLipCorner", "Rotation": {"pitch": 0.0, "roll": 0.0, "yaw": 0.0}, "Scale": {"x": 1.0, "y": 1.0, "z": 1.0}, "Translation": {"x": 0.0, "y": 0.0, "z": 0.0}, "_jwp_arr_idx": 46}, {"BoneName": "R_LowerMouthFold", "Rotation": {"pitch": 0.0, "roll": 0.0, "yaw": 0.0}, "Scale": {"x": 1.0, "y": 1.0, "z": 1.0}, "Translation": {"x": 0.0, "y": 0.0, "z": 0.0}, "_jwp_arr_idx": 47}, {"BoneName": "R_LowerLabiaFold", "Rotation": {"pitch": 0.0, "roll": 0.0, "yaw": 0.0}, "Scale": {"x": 1.0, "y": 1.0, "z": 1.0}, "Translation": {"x": 0.0, "y": 0.0, "z": 0.0}, "_jwp_arr_idx": 48}, {"BoneName": "Jaw_End", "Rotation": {"pitch": 0.0, "roll": 0.0, "yaw": 0.0}, "Scale": {"x": 1.0, "y": 1.0, "z": 1.0}, "Translation": {"x": 0.0, "y": 0.0, "z": 0.0}, "_jwp_arr_idx": 49}, {"BoneName": "R_UpperLip", "Rotation": {"pitch": 0.0, "roll": 0.0, "yaw": 0.0}, "Scale": {"x": 1.0, "y": 1.0, "z": 1.0}, "Translation": {"x": 0.0, "y": 0.0, "z": 0.0}, "_jwp_arr_idx": 50}, {"BoneName": "R_UpperLipCorner", "Rotation": {"pitch": 0.0, "roll": 0.0, "yaw": 0.0}, "Scale": {"x": 1.0, "y": 1.0, "z": 1.0}, "Translation": {"x": 0.0, "y": 0.0, "z": 0.0}, "_jwp_arr_idx": 51}, {"BoneName": "R_MouthCorner", "Rotation": {"pitch": 0.0, "roll": 0.0, "yaw": 0.0}, "Scale": {"x": 1.0, "y": 1.0, "z": 1.0}, "Translation": {"x": 0.0, "y": 0.0, "z": 0.0}, "_jwp_arr_idx": 52}, {"BoneName": "R_Sneer", "Rotation": {"pitch": 0.0, "roll": 0.0, "yaw": 0.0}, "Scale": {"x": 1.0, "y": 1.0, "z": 1.0}, "Translation": {"x": 0.0, "y": 0.0, "z": 0.0}, "_jwp_arr_idx": 53}, {"BoneName": "R_NasalLabiaFold", "Rotation": {"pitch": 0.0, "roll": 0.0, "yaw": 0.0}, "Scale": {"x": 1.0, "y": 1.0, "z": 1.0}, "Translation": {"x": 0.0, "y": 0.0, "z": 0.0}, "_jwp_arr_idx": 54}, {"BoneName": "R_Cheek", "Rotation": {"pitch": 0.0, "roll": 0.0, "yaw": 0.0}, "Scale": {"x": 1.0, "y": 1.0, "z": 1.0}, "Translation": {"x": 0.0, "y": 0.0, "z": 0.0}, "_jwp_arr_idx": 55}, {"BoneName": "R_NasalCorner", "Rotation": {"pitch": 0.0, "roll": 0.0, "yaw": 0.0}, "Scale": {"x": 1.0, "y": 1.0, "z": 1.0}, "Translation": {"x": 0.0, "y": 0.0, "z": 0.0}, "_jwp_arr_idx": 56}, {"BoneName": "R_CheekBone", "Rotation": {"pitch": 0.0, "roll": 0.0, "yaw": 0.0}, "Scale": {"x": 1.0, "y": 1.0, "z": 1.0}, "Translation": {"x": 0.0, "y": 0.0, "z": 0.0}, "_jwp_arr_idx": 57}, {"BoneName": "R_Eye", "Rotation": {"pitch": 0.0, "roll": 0.0, "yaw": 0.0}, "Scale": {"x": 1.0, "y": 1.0, "z": 1.0}, "Translation": {"x": 0.0, "y": 0.0, "z": 0.0}, "_jwp_arr_idx": 58}, {"BoneName": "R_LowerInsideEyelid", "Rotation": {"pitch": 0.0, "roll": 0.0, "yaw": 0.0}, "Scale": {"x": 1.0, "y": 1.0, "z": 1.0}, "Translation": {"x": 0.0, "y": 0.0, "z": 0.0}, "_jwp_arr_idx": 59}, {"BoneName": "R_LowerMiddleEyelid", "Rotation": {"pitch": 0.0, "roll": 0.0, "yaw": 0.0}, "Scale": {"x": 1.0, "y": 1.0, "z": 1.0}, "Translation": {"x": 0.0, "y": 0.0, "z": 0.0}, "_jwp_arr_idx": 60}, {"BoneName": "R_LowerOutsideEyelid", "Rotation": {"pitch": 0.0, "roll": 0.0, "yaw": 0.0}, "Scale": {"x": 1.0, "y": 1.0, "z": 1.0}, "Translation": {"x": 0.0, "y": 0.0, "z": 0.0}, "_jwp_arr_idx": 61}, {"BoneName": "R_UpperInsideEyelid", "Rotation": {"pitch": 0.0, "roll": 0.0, "yaw": 0.0}, "Scale": {"x": 1.0, "y": 1.0, "z": 1.0}, "Translation": {"x": 0.0, "y": 0.0, "z": 0.0}, "_jwp_arr_idx": 62}, {"BoneName": "R_UpperMiddleEyelid", "Rotation": {"pitch": 0.0, "roll": 0.0, "yaw": 0.0}, "Scale": {"x": 1.0, "y": 1.0, "z": 1.0}, "Translation": {"x": 0.0, "y": 0.0, "z": 0.0}, "_jwp_arr_idx": 63}, {"BoneName": "R_UpperOutsideEyelid", "Rotation": {"pitch": 0.0, "roll": 0.0, "yaw": 0.0}, "Scale": {"x": 1.0, "y": 1.0, "z": 1.0}, "Translation": {"x": 0.0, "y": 0.0, "z": 0.0}, "_jwp_arr_idx": 64}, {"BoneName": "R_InnerBrow", "Rotation": {"pitch": 0.0, "roll": 0.0, "yaw": 0.0}, "Scale": {"x": 1.0, "y": 1.0, "z": 1.0}, "Translation": {"x": 0.0, "y": 0.0, "z": 0.0}, "_jwp_arr_idx": 65}, {"BoneName": "R_Brow", "Rotation": {"pitch": 0.0, "roll": 0.0, "yaw": 0.0}, "Scale": {"x": 1.0, "y": 1.0, "z": 1.0}, "Translation": {"x": 0.0, "y": 0.0, "z": 0.0}, "_jwp_arr_idx": 66}, {"BoneName": "R_OuterBrow", "Rotation": {"pitch": 0.0, "roll": 0.0, "yaw": 0.0}, "Scale": {"x": 1.0, "y": 1.0, "z": 1.0}, "Translation": {"x": 0.0, "y": 0.0, "z": 0.0}, "_jwp_arr_idx": 67}, {"BoneName": "R_Forehead", "Rotation": {"pitch": 0.0, "roll": 0.0, "yaw": 0.0}, "Scale": {"x": 1.0, "y": 1.0, "z": 1.0}, "Translation": {"x": 0.0, "y": 0.0, "z": 0.0}, "_jwp_arr_idx": 68}, {"BoneName": "R_NasalFlare", "Rotation": {"pitch": 0.0, "roll": 0.0, "yaw": 0.0}, "Scale": {"x": 1.0, "y": 1.0, "z": 1.0}, "Translation": {"x": 0.0, "y": 0.0, "z": 0.0}, "_jwp_arr_idx": 69}, {"BoneName": "UnderJaw", "Rotation": {"pitch": 0.0, "roll": 0.0, "yaw": 0.0}, "Scale": {"x": 1.0, "y": 1.0, "z": 1.0}, "Translation": {"x": 0.0, "y": 0.0, "z": 0.0}, "_jwp_arr_idx": 70}, {"BoneName": "Bridge", "Rotation": {"pitch": 0.0, "roll": 0.0, "yaw": 0.0}, "Scale": {"x": 1.0, "y": 1.0, "z": 1.0}, "Translation": {"x": 0.0, "y": 0.0, "z": 0.0}, "_jwp_arr_idx": 71}, {"BoneName": "L_Bridge", "Rotation": {"pitch": 0.0, "roll": 0.0, "yaw": 0.0}, "Scale": {"x": 1.0, "y": 1.0, "z": 1.0}, "Translation": {"x": 0.0, "y": 0.0, "z": 0.0}, "_jwp_arr_idx": 72}, {"BoneName": "R_Bridge", "Rotation": {"pitch": 0.0, "roll": 0.0, "yaw": 0.0}, "Scale": {"x": 1.0, "y": 1.0, "z": 1.0}, "Translation": {"x": 0.0, "y": 0.0, "z": 0.0}, "_jwp_arr_idx": 73}, {"BoneName": "L_MidLabiaFold", "Rotation": {"pitch": 0.0, "roll": 0.0, "yaw": 0.0}, "Scale": {"x": 1.0, "y": 1.0, "z": 1.0}, "Translation": {"x": 0.0, "y": 0.0, "z": 0.0}, "_jwp_arr_idx": 74}, {"BoneName": "R_MidLabiaFold", "Rotation": {"pitch": 0.0, "roll": 0.0, "yaw": 0.0}, "Scale": {"x": 1.0, "y": 1.0, "z": 1.0}, "Translation": {"x": 0.0, "y": 0.0, "z": 0.0}, "_jwp_arr_idx": 75}, {"BoneName": "Nose", "Rotation": {"pitch": 0.0, "roll": 0.0, "yaw": 0.0}, "Scale": {"x": 1.0, "y": 1.0, "z": 1.0}, "Translation": {"x": 0.0, "y": 0.0, "z": 0.0}, "_jwp_arr_idx": 76}, {"BoneName": "Mask", "Rotation": {"pitch": 0.0, "roll": 0.0, "yaw": 0.0}, "Scale": {"x": 1.0, "y": 1.0, "z": 1.0}, "Translation": {"x": 0.0, "y": 0.0, "z": 0.0}, "_jwp_arr_idx": 77}, {"BoneName": "Center_MaskStrap", "Rotation": {"pitch": 0.0, "roll": 0.0, "yaw": 0.0}, "Scale": {"x": 1.0, "y": 1.0, "z": 1.0}, "Translation": {"x": 0.0, "y": 0.0, "z": 0.0}, "_jwp_arr_idx": 78}, {"BoneName": "Back_MaskStrap", "Rotation": {"pitch": 0.0, "roll": 0.0, "yaw": 0.0}, "Scale": {"x": 1.0, "y": 1.0, "z": 1.0}, "Translation": {"x": 0.0, "y": 0.0, "z": 0.0}, "_jwp_arr_idx": 79}, {"BoneName": "L_Clav", "Rotation": {"pitch": -7.630728, "roll": 0.6740748, "yaw": 0.1933855}, "Scale": {"x": 0.7, "y": 0.7, "z": 0.7}, "Translation": {"x": 5.0072584, "y": -2.068192, "z": 4.13239}, "_jwp_arr_idx": 80}, {"BoneName": "L_Upperarm", "Rotation": {"pitch": -7.4999094, "roll": 1.5524018, "yaw": 0.2171994}, "Scale": {"x": 1.0, "y": 1.0, "z": 1.0}, "Translation": {"x": 7.6213584, "y": 0.0, "z": 0.0}, "_jwp_arr_idx": 81}, {"BoneName": "L_Forearm", "Rotation": {"pitch": 0.0, "roll": 0.0, "yaw": 0.0}, "Scale": {"x": 1.0, "y": 1.0, "z": 1.0}, "Translation": {"x": 1.5868645, "y": -0.05204606, "z": 0.0}, "_jwp_arr_idx": 82}, {"BoneName": "L_Hand", "Rotation": {"pitch": 0.0, "roll": 0.0, "yaw": 0.0}, "Scale": {"x": 1.0, "y": 1.0, "z": 1.0}, "Translation": {"x": -6.8216286, "y": 0.0, "z": -0.059506103}, "_jwp_arr_idx": 83}, {"BoneName": "L_Hand_Object", "Rotation": {"pitch": 0.0, "roll": 0.0, "yaw": 0.0}, "Scale": {"x": 1.4285716, "y": 1.4285716, "z": 1.4285716}, "Translation": {"x": 0.0, "y": 0.0, "z": 0.0}, "_jwp_arr_idx": 84}, {"BoneName": "L_Thumb_01", "Rotation": {"pitch": 0.0, "roll": 0.0, "yaw": 0.0}, "Scale": {"x": 1.0, "y": 1.0, "z": 1.0}, "Translation": {"x": 0.0, "y": 0.0, "z": 0.0}, "_jwp_arr_idx": 85}, {"BoneName": "L_Thumb_02", "Rotation": {"pitch": 0.0, "roll": 0.0, "yaw": 0.0}, "Scale": {"x": 1.0, "y": 1.0, "z": 1.0}, "Translation": {"x": 0.0, "y": 0.0, "z": 0.0}, "_jwp_arr_idx": 86}, {"BoneName": "L_Thumb_03", "Rotation": {"pitch": 0.0, "roll": 0.0, "yaw": 0.0}, "Scale": {"x": 1.0, "y": 1.0, "z": 1.0}, "Translation": {"x": 0.0, "y": 0.0, "z": 0.0}, "_jwp_arr_idx": 87}, {"BoneName": "L_Index_Meta", "Rotation": {"pitch": 0.0, "roll": 0.0, "yaw": 0.0}, "Scale": {"x": 1.0, "y": 1.0, "z": 1.0}, "Translation": {"x": 0.0, "y": 0.0, "z": 0.0}, "_jwp_arr_idx": 88}, {"BoneName": "L_Index_01", "Rotation": {"pitch": 0.0, "roll": 0.0, "yaw": 0.0}, "Scale": {"x": 1.0, "y": 1.0, "z": 1.0}, "Translation": {"x": 0.0, "y": 0.0, "z": 0.0}, "_jwp_arr_idx": 89}, {"BoneName": "L_Index_02", "Rotation": {"pitch": 0.0, "roll": 0.0, "yaw": 0.0}, "Scale": {"x": 1.0, "y": 1.0, "z": 1.0}, "Translation": {"x": 0.0, "y": 0.0, "z": 0.0}, "_jwp_arr_idx": 90}, {"BoneName": "L_Index_03", "Rotation": {"pitch": 0.0, "roll": 0.0, "yaw": 0.0}, "Scale": {"x": 1.0, "y": 1.0, "z": 1.0}, "Translation": {"x": 0.0, "y": 0.0, "z": 0.0}, "_jwp_arr_idx": 91}, {"BoneName": "L_Middle_Meta", "Rotation": {"pitch": 0.0, "roll": 0.0, "yaw": 0.0}, "Scale": {"x": 1.0, "y": 1.0, "z": 1.0}, "Translation": {"x": 0.0, "y": 0.0, "z": 0.0}, "_jwp_arr_idx": 92}, {"BoneName": "L_Middle_01", "Rotation": {"pitch": 0.0, "roll": 0.0, "yaw": 0.0}, "Scale": {"x": 1.0, "y": 1.0, "z": 1.0}, "Translation": {"x": 0.0, "y": 0.0, "z": 0.0}, "_jwp_arr_idx": 93}, {"BoneName": "L_Middle_02", "Rotation": {"pitch": 0.0, "roll": 0.0, "yaw": 0.0}, "Scale": {"x": 1.0, "y": 1.0, "z": 1.0}, "Translation": {"x": 0.0, "y": 0.0, "z": 0.0}, "_jwp_arr_idx": 94}, {"BoneName": "L_Middle_03", "Rotation": {"pitch": 0.0, "roll": 0.0, "yaw": 0.0}, "Scale": {"x": 1.0, "y": 1.0, "z": 1.0}, "Translation": {"x": 0.0, "y": 0.0, "z": 0.0}, "_jwp_arr_idx": 95}, {"BoneName": "L_Ring_Meta", "Rotation": {"pitch": 0.0, "roll": 0.0, "yaw": 0.0}, "Scale": {"x": 1.0, "y": 1.0, "z": 1.0}, "Translation": {"x": 0.0, "y": 0.0, "z": 0.0}, "_jwp_arr_idx": 96}, {"BoneName": "L_Ring_01", "Rotation": {"pitch": 0.0, "roll": 0.0, "yaw": 0.0}, "Scale": {"x": 1.0, "y": 1.0, "z": 1.0}, "Translation": {"x": 0.0, "y": 0.0, "z": 0.0}, "_jwp_arr_idx": 97}, {"BoneName": "L_Ring_02", "Rotation": {"pitch": 0.0, "roll": 0.0, "yaw": 0.0}, "Scale": {"x": 1.0, "y": 1.0, "z": 1.0}, "Translation": {"x": 0.0, "y": 0.0, "z": 0.0}, "_jwp_arr_idx": 98}, {"BoneName": "L_Ring_03", "Rotation": {"pitch": 0.0, "roll": 0.0, "yaw": 0.0}, "Scale": {"x": 1.0, "y": 1.0, "z": 1.0}, "Translation": {"x": 0.0, "y": 0.0, "z": 0.0}, "_jwp_arr_idx": 99}, {"BoneName": "L_Pinky_Meta", "Rotation": {"pitch": 0.0, "roll": 0.0, "yaw": 0.0}, "Scale": {"x": 1.0, "y": 1.0, "z": 1.0}, "Translation": {"x": 0.0, "y": 0.0, "z": 0.0}, "_jwp_arr_idx": 100}, {"BoneName": "L_Pinky_01", "Rotation": {"pitch": 0.0, "roll": 0.0, "yaw": 0.0}, "Scale": {"x": 1.0, "y": 1.0, "z": 1.0}, "Translation": {"x": 0.0, "y": 0.0, "z": 0.0}, "_jwp_arr_idx": 101}, {"BoneName": "L_Pinky_02", "Rotation": {"pitch": 0.0, "roll": 0.0, "yaw": 0.0}, "Scale": {"x": 1.0, "y": 1.0, "z": 1.0}, "Translation": {"x": 0.0, "y": 0.0, "z": 0.0}, "_jwp_arr_idx": 102}, {"BoneName": "L_Pinky_03", "Rotation": {"pitch": 0.0, "roll": 0.0, "yaw": 0.0}, "Scale": {"x": 1.0, "y": 1.0, "z": 1.0}, "Translation": {"x": 0.0, "y": 0.0, "z": 0.0}, "_jwp_arr_idx": 103}, {"BoneName": "L_Forearm_Twist", "Rotation": {"pitch": 0.0, "roll": 0.0, "yaw": 0.0}, "Scale": {"x": 1.0, "y": 1.0, "z": 1.0}, "Translation": {"x": -3.4108238, "y": 0.0, "z": -0.029747486}, "_jwp_arr_idx": 104}, {"BoneName": "L_Upperarm_Twist", "Rotation": {"pitch": 0.0, "roll": 0.0, "yaw": 0.0}, "Scale": {"x": 1.0, "y": 1.0, "z": 1.0}, "Translation": {"x": 0.79342365, "y": -0.026022911, "z": 0.0}, "_jwp_arr_idx": 105}, {"BoneName": "L_Deltoid", "Rotation": {"pitch": 0.0, "roll": 0.0, "yaw": 0.0}, "Scale": {"x": 1.0, "y": 1.0, "z": 1.0}, "Translation": {"x": 0.04954958, "y": -0.0008878708, "z": 0.020093203}, "_jwp_arr_idx": 106}, {"BoneName": "L_Tricep", "Rotation": {"pitch": 0.0, "roll": 0.0, "yaw": 0.0}, "Scale": {"x": 1.0, "y": 1.0, "z": 1.0}, "Translation": {"x": 0.35578823, "y": -0.008874893, "z": -0.0008380413}, "_jwp_arr_idx": 107}, {"BoneName": "R_Clav", "Rotation": {"pitch": -7.7481594, "roll": -0.084658116, "yaw": 1.2500942}, "Scale": {"x": 2.207, "y": 2.207, "z": 2.207}, "Translation": {"x": 1.6295266, "y": 0.52988386, "z": 1.0865145}, "_jwp_arr_idx": 108}, {"BoneName": "R_Upperarm", "Rotation": {"pitch": -7.8502707, "roll": 0.0, "yaw": 0.0}, "Scale": {"x": 1.1, "y": 1.1, "z": 1.1}, "Translation": {"x": -5.7047787, "y": 0.0, "z": 0.0}, "_jwp_arr_idx": 109}, {"BoneName": "R_Forearm", "Rotation": {"pitch": 0.0, "roll": 0.0, "yaw": 0.0}, "Scale": {"x": 1.031895, "y": 1.031895, "z": 1.031895}, "Translation": {"x": -6.73814, "y": 0.22100067, "z": 0.0}, "_jwp_arr_idx": 110}, {"BoneName": "R_Hand", "Rotation": {"pitch": 0.0, "roll": 0.0, "yaw": 0.0}, "Scale": {"x": 0.9090909, "y": 0.9090909, "z": 0.9090909}, "Translation": {"x": -6.557247, "y": 0.0, "z": 0.0572021}, "_jwp_arr_idx": 111}, {"BoneName": "R_Hand_Object", "Rotation": {"pitch": 0.0, "roll": 0.0, "yaw": 0.0}, "Scale": {"x": 0.5, "y": 0.5, "z": 0.5}, "Translation": {"x": 0.85572815, "y": -0.580493, "z": 0.0}, "_jwp_arr_idx": 112}, {"BoneName": "R_Thumb_01", "Rotation": {"pitch": 0.0, "roll": 0.0, "yaw": 0.0}, "Scale": {"x": 1.0, "y": 1.0, "z": 1.0}, "Translation": {"x": 0.0, "y": 0.0, "z": 0.0}, "_jwp_arr_idx": 113}, {"BoneName": "R_Thumb_02", "Rotation": {"pitch": 0.0, "roll": 0.0, "yaw": 0.0}, "Scale": {"x": 1.0, "y": 1.0, "z": 1.0}, "Translation": {"x": 0.0, "y": 0.0, "z": 0.0}, "_jwp_arr_idx": 114}, {"BoneName": "R_Thumb_03", "Rotation": {"pitch": 0.0, "roll": 0.0, "yaw": 0.0}, "Scale": {"x": 1.0, "y": 1.0, "z": 1.0}, "Translation": {"x": 0.0, "y": 0.0, "z": 0.0}, "_jwp_arr_idx": 115}, {"BoneName": "R_Middle_Meta", "Rotation": {"pitch": 0.0, "roll": 0.0, "yaw": 0.0}, "Scale": {"x": 1.0, "y": 1.0, "z": 1.0}, "Translation": {"x": 0.0, "y": 0.0, "z": 0.0}, "_jwp_arr_idx": 116}, {"BoneName": "R_Middle_01", "Rotation": {"pitch": 0.0, "roll": 0.0, "yaw": 0.0}, "Scale": {"x": 1.0, "y": 1.0, "z": 1.0}, "Translation": {"x": 0.0, "y": 0.0, "z": 0.0}, "_jwp_arr_idx": 117}, {"BoneName": "R_Middle_02", "Rotation": {"pitch": 0.0, "roll": 0.0, "yaw": 0.0}, "Scale": {"x": 1.0, "y": 1.0, "z": 1.0}, "Translation": {"x": 0.0, "y": 0.0, "z": 0.0}, "_jwp_arr_idx": 118}, {"BoneName": "R_Middle_03", "Rotation": {"pitch": 0.0, "roll": 0.0, "yaw": 0.0}, "Scale": {"x": 1.0, "y": 1.0, "z": 1.0}, "Translation": {"x": 0.0, "y": 0.0, "z": 0.0}, "_jwp_arr_idx": 119}, {"BoneName": "R_Index_Meta", "Rotation": {"pitch": 0.0, "roll": 0.0, "yaw": 0.0}, "Scale": {"x": 1.0, "y": 1.0, "z": 1.0}, "Translation": {"x": 0.0, "y": 0.0, "z": 0.0}, "_jwp_arr_idx": 120}, {"BoneName": "R_Index_01", "Rotation": {"pitch": 0.0, "roll": 0.0, "yaw": 0.0}, "Scale": {"x": 1.0, "y": 1.0, "z": 1.0}, "Translation": {"x": 0.0, "y": 0.0, "z": 0.0}, "_jwp_arr_idx": 121}, {"BoneName": "R_Index_02", "Rotation": {"pitch": 0.0, "roll": 0.0, "yaw": 0.0}, "Scale": {"x": 1.0, "y": 1.0, "z": 1.0}, "Translation": {"x": 0.0, "y": 0.0, "z": 0.0}, "_jwp_arr_idx": 122}, {"BoneName": "R_Index_03", "Rotation": {"pitch": 0.0, "roll": 0.0, "yaw": 0.0}, "Scale": {"x": 1.0, "y": 1.0, "z": 1.0}, "Translation": {"x": 0.0, "y": 0.0, "z": 0.0}, "_jwp_arr_idx": 123}, {"BoneName": "R_Ring_Meta", "Rotation": {"pitch": 0.0, "roll": 0.0, "yaw": 0.0}, "Scale": {"x": 1.0, "y": 1.0, "z": 1.0}, "Translation": {"x": 0.0, "y": 0.0, "z": 0.0}, "_jwp_arr_idx": 124}, {"BoneName": "R_Ring_01", "Rotation": {"pitch": 0.0, "roll": 0.0, "yaw": 0.0}, "Scale": {"x": 1.0, "y": 1.0, "z": 1.0}, "Translation": {"x": 0.0, "y": 0.0, "z": 0.0}, "_jwp_arr_idx": 125}, {"BoneName": "R_Ring_02", "Rotation": {"pitch": 0.0, "roll": 0.0, "yaw": 0.0}, "Scale": {"x": 1.0, "y": 1.0, "z": 1.0}, "Translation": {"x": 0.0, "y": 0.0, "z": 0.0}, "_jwp_arr_idx": 126}, {"BoneName": "R_Ring_03", "Rotation": {"pitch": 0.0, "roll": 0.0, "yaw": 0.0}, "Scale": {"x": 1.0, "y": 1.0, "z": 1.0}, "Translation": {"x": 0.0, "y": 0.0, "z": 0.0}, "_jwp_arr_idx": 127}, {"BoneName": "R_Pinky_Meta", "Rotation": {"pitch": 0.0, "roll": 0.0, "yaw": 0.0}, "Scale": {"x": 1.0, "y": 1.0, "z": 1.0}, "Translation": {"x": 0.0, "y": 0.0, "z": 0.0}, "_jwp_arr_idx": 128}, {"BoneName": "R_Pinky_01", "Rotation": {"pitch": 0.0, "roll": 0.0, "yaw": 0.0}, "Scale": {"x": 1.0, "y": 1.0, "z": 1.0}, "Translation": {"x": 0.0, "y": 0.0, "z": 0.0}, "_jwp_arr_idx": 129}, {"BoneName": "R_Pinky_02", "Rotation": {"pitch": 0.0, "roll": 0.0, "yaw": 0.0}, "Scale": {"x": 1.0, "y": 1.0, "z": 1.0}, "Translation": {"x": 0.0, "y": 0.0, "z": 0.0}, "_jwp_arr_idx": 130}, {"BoneName": "R_Pinky_03", "Rotation": {"pitch": 0.0, "roll": 0.0, "yaw": 0.0}, "Scale": {"x": 1.0, "y": 1.0, "z": 1.0}, "Translation": {"x": 0.0, "y": 0.0, "z": 0.0}, "_jwp_arr_idx": 131}, {"BoneName": "R_Forearm_Twist", "Rotation": {"pitch": 0.0, "roll": 0.0, "yaw": 0.0}, "Scale": {"x": 1.0, "y": 1.0, "z": 1.0}, "Translation": {"x": -3.2786224, "y": 0.0, "z": 0.028601885}, "_jwp_arr_idx": 132}, {"BoneName": "R_Upperarm_Twist", "Rotation": {"pitch": 0.0, "roll": 0.0, "yaw": 0.0}, "Scale": {"x": 1.0, "y": 1.0, "z": 1.0}, "Translation": {"x": -3.3690662, "y": 0.110500336, "z": 0.0}, "_jwp_arr_idx": 133}, {"BoneName": "R_Deltoid", "Rotation": {"pitch": 0.0, "roll": 0.0, "yaw": 0.0}, "Scale": {"x": 1.0, "y": 1.0, "z": 1.0}, "Translation": {"x": -0.036513448, "y": 0.0014629364, "z": 0.00855957}, "_jwp_arr_idx": 134}, {"BoneName": "R_Tricep", "Rotation": {"pitch": 0.0, "roll": 0.0, "yaw": 0.0}, "Scale": {"x": 1.0, "y": 1.0, "z": 1.0}, "Translation": {"x": -1.408576, "y": 0.05003071, "z": 0.01681614}, "_jwp_arr_idx": 135}, {"BoneName": "L_Hand_Weapon", "Rotation": {"pitch": 0.0, "roll": 0.0, "yaw": 0.0}, "Scale": {"x": 1.0, "y": 1.0, "z": 1.0}, "Translation": {"x": 0.0, "y": 0.0, "z": 0.0}, "_jwp_arr_idx": 136}, {"BoneName": "R_Hand_Weapon", "Rotation": {"pitch": 0.0, "roll": 0.0, "yaw": 0.0}, "Scale": {"x": 1.0, "y": 1.0, "z": 1.0}, "Translation": {"x": 0.0, "y": 0.0, "z": 0.0}, "_jwp_arr_idx": 137}, {"BoneName": "Camera", "Rotation": {"pitch": 0.0, "roll": 0.0, "yaw": 0.0}, "Scale": {"x": 1.0, "y": 1.0, "z": 1.0}, "Translation": {"x": -4.8728485, "y": -1.4137192, "z": 0.0}, "_jwp_arr_idx": 138}, {"BoneName": "L_Hand_to_Camera_1st", "Rotation": {"pitch": 0.0, "roll": 0.0, "yaw": 0.0}, "Scale": {"x": 1.0, "y": 1.0, "z": 1.0}, "Translation": {"x": 0.0, "y": 0.0, "z": 0.0}, "_jwp_arr_idx": 139}, {"BoneName": "R_Hand_to_Camera_1st", "Rotation": {"pitch": 0.0, "roll": 0.0, "yaw": 0.0}, "Scale": {"x": 1.0, "y": 1.0, "z": 1.0}, "Translation": {"x": 0.0, "y": 0.0, "z": 0.0}, "_jwp_arr_idx": 140}, {"BoneName": "Canister10", "Rotation": {"pitch": 0.0, "roll": 0.0, "yaw": 0.0}, "Scale": {"x": 1.0, "y": 1.0, "z": 1.0}, "Translation": {"x": 3.842239, "y": 11.100359, "z": 7.414894}, "_jwp_arr_idx": 141}, {"BoneName": "Canister09", "Rotation": {"pitch": 0.0, "roll": 0.0, "yaw": 0.0}, "Scale": {"x": 1.0, "y": 1.0, "z": 1.0}, "Translation": {"x": 7.6519694, "y": 6.669178, "z": 8.45315}, "_jwp_arr_idx": 142}, {"BoneName": "Canister08", "Rotation": {"pitch": 0.0, "roll": 0.0, "yaw": 0.0}, "Scale": {"x": 1.0, "y": 1.0, "z": 1.0}, "Translation": {"x": -5.1287956, "y": 11.699685, "z": -8.426494}, "_jwp_arr_idx": 143}, {"BoneName": "Canister07", "Rotation": {"pitch": 0.0, "roll": 0.0, "yaw": 0.0}, "Scale": {"x": 1.0, "y": 1.0, "z": 1.0}, "Translation": {"x": -0.652267, "y": 10.575938, "z": -10.529195}, "_jwp_arr_idx": 144}, {"BoneName": "Canister06", "Rotation": {"pitch": -7.7481594, "roll": -0.084658116, "yaw": 1.2500942}, "Scale": {"x": 1.0, "y": 1.0, "z": 1.0}, "Translation": {"x": -0.16130638, "y": 3.9669113, "z": -3.9220352}, "_jwp_arr_idx": 145}, {"BoneName": "Canister05", "Rotation": {"pitch": -7.7481594, "roll": -0.084658116, "yaw": 1.2500942}, "Scale": {"x": 1.0, "y": 1.0, "z": 1.0}, "Translation": {"x": 0.9728341, "y": 2.2204869, "z": -4.8298187}, "_jwp_arr_idx": 146}, {"BoneName": "Canister04", "Rotation": {"pitch": -7.7481594, "roll": -0.084658116, "yaw": 1.2500942}, "Scale": {"x": 1.0, "y": 1.0, "z": 1.0}, "Translation": {"x": 0.7961507, "y": 0.2514875, "z": -4.601571}, "_jwp_arr_idx": 147}, {"BoneName": "Canister03", "Rotation": {"pitch": -7.7481594, "roll": -0.084658116, "yaw": 1.2500942}, "Scale": {"x": 1.0, "y": 1.0, "z": 1.0}, "Translation": {"x": 0.03447342, "y": -1.8628993, "z": -3.0802803}, "_jwp_arr_idx": 148}, {"BoneName": "Canister02", "Rotation": {"pitch": 0.0, "roll": 0.0, "yaw": 0.0}, "Scale": {"x": 1.0, "y": 1.0, "z": 1.0}, "Translation": {"x": -2.5015602, "y": -8.72667, "z": -9.788252}, "_jwp_arr_idx": 149}, {"BoneName": "Canister01", "Rotation": {"pitch": 0.0, "roll": 0.0, "yaw": 0.0}, "Scale": {"x": 1.0, "y": 1.0, "z": 1.0}, "Translation": {"x": -7.3876114, "y": -11.895986, "z": -7.4730835}, "_jwp_arr_idx": 150}, {"BoneName": "Backpack", "Rotation": {"pitch": 0.0, "roll": 0.0, "yaw": 0.0}, "Scale": {"x": 0.8278146, "y": 0.8278146, "z": 0.8278146}, "Translation": {"x": 0.25722396, "y": -2.0463572, "z": 0.0}, "_jwp_arr_idx": 151}, {"BoneName": "L_Thigh", "Rotation": {"pitch": 0.0, "roll": 0.0, "yaw": 0.0}, "Scale": {"x": 1.017294, "y": 1.017294, "z": 1.017294}, "Translation": {"x": -0.092657566, "y": 0.0, "z": 0.15342903}, "_jwp_arr_idx": 152}, {"BoneName": "L_Shin", "Rotation": {"pitch": 0.0, "roll": 0.0, "yaw": 0.0}, "Scale": {"x": 1.0, "y": 1.0, "z": 1.0}, "Translation": {"x": 0.0, "y": 0.0, "z": 0.0}, "_jwp_arr_idx": 153}, {"BoneName": "L_Foot", "Rotation": {"pitch": 0.0, "roll": 0.0, "yaw": 0.0}, "Scale": {"x": 1.0, "y": 1.0, "z": 1.0}, "Translation": {"x": 0.0, "y": 0.0, "z": 0.0}, "_jwp_arr_idx": 154}, {"BoneName": "L_Toe", "Rotation": {"pitch": 0.0, "roll": 0.0, "yaw": 0.0}, "Scale": {"x": 1.0, "y": 1.0, "z": 1.0}, "Translation": {"x": 0.0, "y": 0.0, "z": 0.0}, "_jwp_arr_idx": 155}, {"BoneName": "Knife", "Rotation": {"pitch": 0.0, "roll": 0.0, "yaw": 0.0}, "Scale": {"x": 1.0, "y": 1.0, "z": 1.0}, "Translation": {"x": 0.0, "y": 0.0, "z": 0.0}, "_jwp_arr_idx": 156}, {"BoneName": "BL_Chain_01", "Rotation": {"pitch": 0.0, "roll": 0.0, "yaw": 0.0}, "Scale": {"x": 1.0, "y": 1.0, "z": 1.0}, "Translation": {"x": 0.0, "y": 0.0, "z": 0.0}, "_jwp_arr_idx": 157}, {"BoneName": "BL_Chain_02", "Rotation": {"pitch": 0.0, "roll": 0.0, "yaw": 0.0}, "Scale": {"x": 1.0, "y": 1.0, "z": 1.0}, "Translation": {"x": 0.0, "y": 0.0, "z": 0.0}, "_jwp_arr_idx": 158}, {"BoneName": "L_Chain_01", "Rotation": {"pitch": 0.0, "roll": 0.0, "yaw": 0.0}, "Scale": {"x": 1.0, "y": 1.0, "z": 1.0}, "Translation": {"x": 0.0, "y": 0.0, "z": 0.0}, "_jwp_arr_idx": 159}, {"BoneName": "L_Chain_02", "Rotation": {"pitch": 0.0, "roll": 0.0, "yaw": 0.0}, "Scale": {"x": 1.0, "y": 1.0, "z": 1.0}, "Translation": {"x": 0.0, "y": 0.0, "z": 0.0}, "_jwp_arr_idx": 160}, {"BoneName": "FL_Chain_02", "Rotation": {"pitch": 0.0, "roll": 0.0, "yaw": 0.0}, "Scale": {"x": 1.0, "y": 1.0, "z": 1.0}, "Translation": {"x": 0.0, "y": 0.0, "z": 0.0}, "_jwp_arr_idx": 161}, {"BoneName": "FL_Chain_01", "Rotation": {"pitch": 0.0, "roll": 0.0, "yaw": 0.0}, "Scale": {"x": 1.0, "y": 1.0, "z": 1.0}, "Translation": {"x": 0.0, "y": 0.0, "z": 0.0}, "_jwp_arr_idx": 162}, {"BoneName": "F_Chain_02", "Rotation": {"pitch": 0.0, "roll": 0.0, "yaw": 0.0}, "Scale": {"x": 1.0, "y": 1.0, "z": 1.0}, "Translation": {"x": 0.0, "y": 0.0, "z": 0.0}, "_jwp_arr_idx": 163}, {"BoneName": "F_Chain_01", "Rotation": {"pitch": 0.0, "roll": 0.0, "yaw": 0.0}, "Scale": {"x": 1.0, "y": 1.0, "z": 1.0}, "Translation": {"x": 0.0, "y": 0.0, "z": 0.0}, "_jwp_arr_idx": 164}, {"BoneName": "R_Thigh", "Rotation": {"pitch": 0.0, "roll": 0.0, "yaw": 0.0}, "Scale": {"x": 1.017294, "y": 1.017294, "z": 1.017294}, "Translation": {"x": -0.092657566, "y": 0.0, "z": -0.15342903}, "_jwp_arr_idx": 165}, {"BoneName": "R_Shin", "Rotation": {"pitch": 0.0, "roll": 0.0, "yaw": 0.0}, "Scale": {"x": 1.0, "y": 1.0, "z": 1.0}, "Translation": {"x": 0.0, "y": 0.0, "z": 0.0}, "_jwp_arr_idx": 166}, {"BoneName": "R_Foot", "Rotation": {"pitch": 0.0, "roll": 0.0, "yaw": 0.0}, "Scale": {"x": 1.0, "y": 1.0, "z": 1.0}, "Translation": {"x": 0.0, "y": 0.0, "z": 0.0}, "_jwp_arr_idx": 167}, {"BoneName": "R_Toe", "Rotation": {"pitch": 0.0, "roll": 0.0, "yaw": 0.0}, "Scale": {"x": 1.0, "y": 1.0, "z": 1.0}, "Translation": {"x": 0.0, "y": 0.0, "z": 0.0}, "_jwp_arr_idx": 168}, {"BoneName": "Carabiner", "Rotation": {"pitch": 0.0, "roll": 0.0, "yaw": 0.0}, "Scale": {"x": 1.0, "y": 1.0, "z": 1.0}, "Translation": {"x": 0.0, "y": 0.0, "z": 0.0}, "_jwp_arr_idx": 169}, {"BoneName": "F_ChainRing", "Rotation": {"pitch": 0.0, "roll": 0.0, "yaw": 0.0}, "Scale": {"x": 1.0, "y": 1.0, "z": 1.0}, "Translation": {"x": 0.0, "y": 0.0, "z": 0.0}, "_jwp_arr_idx": 170}, {"BoneName": "B_ChainRing", "Rotation": {"pitch": 0.0, "roll": 0.0, "yaw": 0.0}, "Scale": {"x": 1.0, "y": 1.0, "z": 1.0}, "Translation": {"x": 0.0, "y": 0.0, "z": 0.0}, "_jwp_arr_idx": 171}, {"BoneName": "L_Belt_01", "Rotation": {"pitch": 0.0, "roll": 0.0, "yaw": 0.0}, "Scale": {"x": 1.017294, "y": 1.017294, "z": 1.017294}, "Translation": {"x": -0.023682952, "y": 0.026536942, "z": 0.284773}, "_jwp_arr_idx": 172}, {"BoneName": "FR_Belt_01", "Rotation": {"pitch": 0.0, "roll": 0.0, "yaw": 0.0}, "Scale": {"x": 1.017294, "y": 1.017294, "z": 1.017294}, "Translation": {"x": -0.053759575, "y": -0.18419838, "z": -0.18502998}, "_jwp_arr_idx": 173}, {"BoneName": "R_Belt_01", "Rotation": {"pitch": 0.0, "roll": 0.0, "yaw": 0.0}, "Scale": {"x": 1.017294, "y": 1.017294, "z": 1.017294}, "Translation": {"x": -0.0067005157, "y": 0.026538849, "z": -0.28487015}, "_jwp_arr_idx": 174}, {"BoneName": "BR_Belt_01", "Rotation": {"pitch": 0.0, "roll": 0.0, "yaw": 0.0}, "Scale": {"x": 1.017294, "y": 1.017294, "z": 1.017294}, "Translation": {"x": 0.014685392, "y": 0.18797016, "z": -0.17828083}, "_jwp_arr_idx": 175}, {"BoneName": "Grenade_03", "Rotation": {"pitch": 0.0, "roll": 0.0, "yaw": 0.0}, "Scale": {"x": 1.0, "y": 1.0, "z": 1.0}, "Translation": {"x": 0.0, "y": 0.0, "z": 0.0}, "_jwp_arr_idx": 176}, {"BoneName": "Grenade_02", "Rotation": {"pitch": 0.0, "roll": 0.0, "yaw": 0.0}, "Scale": {"x": 1.0, "y": 1.0, "z": 1.0}, "Translation": {"x": 0.0, "y": 0.0, "z": 0.0}, "_jwp_arr_idx": 177}, {"BoneName": "B_Belt_01", "Rotation": {"pitch": 0.0, "roll": 0.0, "yaw": 0.0}, "Scale": {"x": 1.017294, "y": 1.017294, "z": 1.017294}, "Translation": {"x": 0.0076881647, "y": 0.2085123, "z": 0.0}, "_jwp_arr_idx": 178}, {"BoneName": "F_Belt_01", "Rotation": {"pitch": 0.0, "roll": 0.0, "yaw": 0.0}, "Scale": {"x": 1.017294, "y": 1.017294, "z": 1.017294}, "Translation": {"x": -0.05748844, "y": -0.25299358, "z": 0.0}, "_jwp_arr_idx": 179}, {"BoneName": "FL_Belt_01", "Rotation": {"pitch": 0.0, "roll": 0.0, "yaw": 0.0}, "Scale": {"x": 1.017294, "y": 1.017294, "z": 1.017294}, "Translation": {"x": -0.053767204, "y": -0.1842041, "z": 0.18502998}, "_jwp_arr_idx": 180}, {"BoneName": "BL_Belt_01", "Rotation": {"pitch": 0.0, "roll": 0.0, "yaw": 0.0}, "Scale": {"x": 1.017294, "y": 1.017294, "z": 1.017294}, "Translation": {"x": -0.003944397, "y": 0.18797302, "z": 0.17827892}, "_jwp_arr_idx": 181}, {"BoneName": "Grenade_01", "Rotation": {"pitch": 0.0, "roll": 0.0, "yaw": 0.0}, "Scale": {"x": 1.0, "y": 1.0, "z": 1.0}, "Translation": {"x": 0.0, "y": 0.0, "z": 0.0}, "_jwp_arr_idx": 182}], "Name": "Default", "PoseMode": "EGbxBoneModifyProfile_PoseMode::Additive", "_jwp_arr_idx": 0, "bStartActive": true}], "_apoc_data_ver": 17, "_jwp_export_idx": 1, "_jwp_is_asset": true, "_jwp_object_name": "BMP_OnePunch", "export_type": "GbxBoneModifyProfile"}]