[{"InheritableComponentHandler": {"_jwp_export_dst_name": "InheritableComponentHandler", "_jwp_export_dst_type": "InheritableComponentHandler", "export": 10}, "SimpleConstructionScript": {"_jwp_export_dst_name": "SimpleConstructionScript_0", "_jwp_export_dst_type": "SimpleConstructionScript", "export": 14}, "_apoc_data_ver": 17, "_jwp_export_idx": 1, "_jwp_is_asset": false, "_jwp_object_name": "BP_HijackCarParts_03_Desert2_C", "export_type": "BlueprintGeneratedClass"}, {"CarPartMesh": ["SM_Veh_Technical_Wheel_Barbed", "/Game/Vehicles/Technical/Model/Meshes/SM_Veh_Technical_Wheel_Barbed"], "FlavorTextElements": [{"Condition": {"_jwp_export_dst_name": "Condition_Condition_IOTrophyState", "_jwp_export_dst_type": "Condition_IOTrophyState_C", "export": 4}, "TextToAdd": {"key": "5252296C4E716F38092AFFA674717304", "namespace": "", "string": "Location: ???"}, "_jwp_arr_idx": 0}, {"Condition": {"_jwp_export_dst_name": "Condition_GbxCondition_Compound_0", "_jwp_export_dst_type": "GbxCondition_Compound", "export": 9}, "TextToAdd": {"key": "6A204C1A40A701E4CC32C586C2D459F4", "namespace": "", "string": "Location: Devil's Razor <br>"}, "_jwp_arr_idx": 1}, {"Condition": {"_jwp_export_dst_name": "Condition_Condition_IOTrophyState_0", "_jwp_export_dst_type": "Condition_IOTrophyState_C", "export": 5}, "TextToAdd": {"key": "086C8600414A0424AF2076B4EC86AF68", "namespace": "", "string": "All-terrain badassery with the added bonus of more ramming damage against flesh."}, "_jwp_arr_idx": 2}], "HijackChallenge": ["Challenge_HiJack_CrewChallengesReward_C", "/Game/GameData/Challenges/_Test/ChallengeRewardTest/Challenge_HiJack_CrewChallengesReward"], "HoloMaterial": ["MI_FX_IO_Veh_Technical_MonsterWheels", "/Game/InteractiveObjects/MissionPlaceables/Effects/Materials/IO_MaterialInstances/MI_FX_IO_Veh_Technical_MonsterWheels"], "RemoteRole": "ROLE_None", "RootComponent": {"_jwp_export_dst_name": "RootComponent", "_jwp_export_dst_type": "SceneComponent", "export": 12}, "TitleText": {"key": "7C83CE86435112BE30BEF59E737B3E8B", "namespace": "", "string": "Monster Wheels"}, "_jwp_export_idx": 2, "_jwp_is_asset": false, "_jwp_object_name": "Default__BP_HijackCarParts_03_Desert2_C", "export_type": "BP_HijackCarParts_03_Desert2_C"}, {"RelativeLocation": {"x": 8.0, "y": 0.0, "z": 0.0}, "RelativeScale3D": {"x": 3.28225, "y": 2.84475, "z": 2.21975}, "_jwp_export_idx": 3, "_jwp_is_asset": false, "_jwp_object_name": "Box_GEN_VARIABLE", "export_type": "BoxComponent"}, {"_jwp_export_idx": 4, "_jwp_is_asset": false, "_jwp_object_name": "Condition_Condition_IOTrophyState", "export_type": "Condition_IOTrophyState_C"}, {"Current State": "Enum_TrophyState::NewEnumerator2", "_jwp_export_idx": 5, "_jwp_is_asset": false, "_jwp_object_name": "Condition_Condition_IOTrophyState_0", "export_type": "Condition_IOTrophyState_C"}, {"Current State": "Enum_TrophyState::NewEnumerator1", "_jwp_export_idx": 6, "_jwp_is_asset": false, "_jwp_object_name": "Condition1_Condition_IOTrophyState", "export_type": "Condition_IOTrophyState_C"}, {"Current State": "Enum_TrophyState::NewEnumerator2", "_jwp_export_idx": 7, "_jwp_is_asset": false, "_jwp_object_name": "Condition2_Condition_IOTrophyState", "export_type": "Condition_IOTrophyState_C"}, {"_jwp_export_idx": 8, "_jwp_is_asset": false, "_jwp_object_name": "Condition_Condition_IsTrue", "export_type": "Condition_IsTrue_C"}, {"Condition1": {"_jwp_export_dst_name": "Condition1_Condition_IOTrophyState", "_jwp_export_dst_type": "Condition_IOTrophyState_C", "export": 6}, "Condition2": {"_jwp_export_dst_name": "Condition2_Condition_IOTrophyState", "_jwp_export_dst_type": "Condition_IOTrophyState_C", "export": 7}, "Operator": "ECompoundConditionOperatorType::Or", "_jwp_export_idx": 9, "_jwp_is_asset": false, "_jwp_object_name": "Condition_GbxCondition_Compound_0", "export_type": "GbxCondition_Compound"}, {"Records": [{"ComponentClass": ["BoxComponent", "/Script/Engine"], "ComponentKey": {"AssociatedGuid": "33970acf4c5739b2ad674487f508a160", "OwnerClass": ["BP_HijackCarParts_C", "/Game/InteractiveObjects/GameSystemMachines/HijackCarParts/BP_HijackCarParts"], "SCSVariableName": "Box"}, "ComponentTemplate": {"_jwp_export_dst_name": "Box_GEN_VARIABLE", "_jwp_export_dst_type": "BoxComponent", "export": 3}, "CookedComponentInstancingData": {"ChangedPropertyList": [], "bIsValid": false}, "_jwp_arr_idx": 0}, {"ComponentClass": ["StaticMeshComponent", "/Script/Engine"], "ComponentKey": {"AssociatedGuid": "61573259442c9fe4a03bb0b150261b4c", "OwnerClass": ["BP_HijackCarParts_C", "/Game/InteractiveObjects/GameSystemMachines/HijackCarParts/BP_HijackCarParts"], "SCSVariableName": "Part"}, "ComponentTemplate": {"_jwp_export_dst_name": "Part_GEN_VARIABLE", "_jwp_export_dst_type": "StaticMeshComponent", "export": 15}, "CookedComponentInstancingData": {"ChangedPropertyList": [], "bIsValid": false}, "_jwp_arr_idx": 1}], "_jwp_export_idx": 10, "_jwp_is_asset": false, "_jwp_object_name": "InheritableComponentHandler", "export_type": "InheritableComponentHandler"}, {"_jwp_export_idx": 11, "_jwp_is_asset": false, "_jwp_object_name": "DefaultSceneRoot_GEN_VARIABLE", "export_type": "SceneComponent"}, {"_jwp_export_idx": 12, "_jwp_is_asset": false, "_jwp_object_name": "RootComponent", "export_type": "SceneComponent"}, {"ComponentClass": ["SceneComponent", "/Script/Engine"], "ComponentTemplate": {"_jwp_export_dst_name": "DefaultSceneRoot_GEN_VARIABLE", "_jwp_export_dst_type": "SceneComponent", "export": 11}, "InternalVariableName": "DefaultSceneRoot", "VariableGuid": "dc165de2448678fd41ba6d8349477e76", "_jwp_export_idx": 13, "_jwp_is_asset": false, "_jwp_object_name": "SCS_Node_0", "export_type": "SCS_Node"}, {"DefaultSceneRootNode": {"_jwp_export_dst_name": "SCS_Node_0", "_jwp_export_dst_type": "SCS_Node", "export": 13}, "_jwp_export_idx": 14, "_jwp_is_asset": false, "_jwp_object_name": "SimpleConstructionScript_0", "export_type": "SimpleConstructionScript"}, {"RelativeLocation": {"x": 0.0, "y": 0.0, "z": 0.0}, "_jwp_export_idx": 15, "_jwp_is_asset": false, "_jwp_object_name": "Part_GEN_VARIABLE", "export_type": "StaticMeshComponent"}, {"_jwp_export_idx": 16, "_jwp_is_asset": false, "_jwp_object_name": "DefaultUsableComponent", "export_type": "UsableComponent"}]