[{"CategoryDisplayName": {"key": "EC25943A4C3AA42D263F5BA030659F18", "namespace": "", "string": "CSBucks"}, "PickupActionType": "EPickupActionType::OnUseOrTouch", "SharedWithAllPlayers": true, "_apoc_data_ver": 17, "_jwp_export_idx": 1, "_jwp_is_asset": true, "_jwp_object_name": "InventoryCategory_CSBucks", "bCanChangeSkins": false, "bCanInspectElementalEffects": false, "bCanInspectItem": false, "bCanInspectManufacturer": false, "bCanInspectParts": false, "bIsPremiumCurrencyCategory": true, "bSharedPlayersMustBeOnFriendlyTeam": false, "export_type": "InventoryCategoryData"}]