[{"DisplayNameMap": [{"_jwp_arr_idx": 0, "key": "NewEnumerator0", "value": {"key": "B801446E496639E2E7BAB99283EA2E64", "namespace": "", "string": "Default"}}, {"_jwp_arr_idx": 1, "key": "NewEnumerator1", "value": {"key": "03DA3A5F426C0BA919820D956D85E8EE", "namespace": "", "string": "Blowable"}}, {"_jwp_arr_idx": 2, "key": "NewEnumerator3", "value": {"key": "449EC9284FE70C32F1DFEEAE39DBB5BD", "namespace": "", "string": "Blown"}}], "_apoc_data_ver": 17, "_jwp_export_idx": 1, "_jwp_is_asset": true, "_jwp_object_name": "Enum_Ali_FleshHornState", "export_type": "UserDefinedEnum"}]