[{"DisplayIcon": ["AssaultRifleAmmoIcon", "/Game/UI/_Shared/Textures/AmmoTypes/AssaultRifleAmmoIcon"], "DisplayName": {"key": "14D33F34425A099C884A6286B16B4F5A", "namespace": "", "string": "Assault Rifle Ammo"}, "ResourceData": ["Resource_Ammo_AssaultRifle", "/Game/GameData/Weapons/Ammo/Resource_Ammo_AssaultRifle"], "ScaleformDisplayFrameID": "assaultRifle", "_apoc_data_ver": 17, "_jwp_export_idx": 1, "_jwp_is_asset": true, "_jwp_object_name": "AmmoType_AssaultRifle", "export_type": "GbxAmmoTypeData"}]